plancraft/__init__.py
plancraft/config.py
plancraft/evaluator.py
plancraft/utils.py
plancraft/environments/__init__.py
plancraft/environments/actions.py
plancraft/environments/constants.json
plancraft/environments/env_real.py
plancraft/environments/env_symbolic.py
plancraft/environments/items.py
plancraft/environments/planner.py
plancraft/environments/recipes.py
plancraft/environments/sampler.py
plancraft/environments/recipes/acacia_boat.json
plancraft/environments/recipes/acacia_button.json
plancraft/environments/recipes/acacia_door.json
plancraft/environments/recipes/acacia_fence.json
plancraft/environments/recipes/acacia_fence_gate.json
plancraft/environments/recipes/acacia_planks.json
plancraft/environments/recipes/acacia_pressure_plate.json
plancraft/environments/recipes/acacia_sign.json
plancraft/environments/recipes/acacia_slab.json
plancraft/environments/recipes/acacia_stairs.json
plancraft/environments/recipes/acacia_trapdoor.json
plancraft/environments/recipes/acacia_wood.json
plancraft/environments/recipes/activator_rail.json
plancraft/environments/recipes/andesite.json
plancraft/environments/recipes/andesite_slab.json
plancraft/environments/recipes/andesite_slab_from_andesite_stonecutting.json
plancraft/environments/recipes/andesite_stairs.json
plancraft/environments/recipes/andesite_stairs_from_andesite_stonecutting.json
plancraft/environments/recipes/andesite_wall.json
plancraft/environments/recipes/andesite_wall_from_andesite_stonecutting.json
plancraft/environments/recipes/anvil.json
plancraft/environments/recipes/armor_dye.json
plancraft/environments/recipes/armor_stand.json
plancraft/environments/recipes/arrow.json
plancraft/environments/recipes/baked_potato.json
plancraft/environments/recipes/baked_potato_from_campfire_cooking.json
plancraft/environments/recipes/baked_potato_from_smoking.json
plancraft/environments/recipes/banner_duplicate.json
plancraft/environments/recipes/barrel.json
plancraft/environments/recipes/beacon.json
plancraft-0.1.4.dist-info/LICENSE
plancraft-0.1.4.dist-info/METADATA
plancraft-0.1.4.dist-info/WHEEL
plancraft-0.1.4.dist-info/top_level.txt
plancraft-0.1.4.dist-info/RECORD
